fakts_next/__init__.py
fakts_next/errors.py
fakts_next/fakts.py
fakts_next/helpers.py
fakts_next/models.py
fakts_next/protocols.py
fakts_next/py.typed
fakts_next/utils.py
fakts_next/cache/file.py
fakts_next/cache/model.py
fakts_next/cache/nocache.py
fakts_next/cache/qt/settings.py
fakts_next/contrib/__init__.py
fakts_next/contrib/rath/__init__.py
fakts_next/contrib/rath/aiohttp.py
fakts_next/contrib/rath/auth.py
fakts_next/contrib/rath/graphql_ws.py
fakts_next/contrib/rath/httpx.py
fakts_next/contrib/rath/subscription_transport_ws.py
fakts_next/grants/__init__.py
fakts_next/grants/base.py
fakts_next/grants/env.py
fakts_next/grants/errors.py
fakts_next/grants/hard.py
fakts_next/grants/oauth/utils.py
fakts_next/grants/remote/__init__.py
fakts_next/grants/remote/base.py
fakts_next/grants/remote/builders.py
fakts_next/grants/remote/errors.py
fakts_next/grants/remote/models.py
fakts_next/grants/remote/claimers/__init__.py
fakts_next/grants/remote/claimers/post.py
fakts_next/grants/remote/claimers/static.py
fakts_next/grants/remote/demanders/__init__.py
fakts_next/grants/remote/demanders/device_code.py
fakts_next/grants/remote/demanders/redeem.py
fakts_next/grants/remote/demanders/retrieve.py
fakts_next/grants/remote/demanders/static.py
fakts_next/grants/remote/demanders/utils.py
fakts_next/grants/remote/demanders/qt/__init__.py
fakts_next/grants/remote/demanders/qt/auto_save_token_widget.py
fakts_next/grants/remote/demanders/qt/qt_settings_token_store.py
fakts_next/grants/remote/discovery/__init__.py
fakts_next/grants/remote/discovery/advertised.py
fakts_next/grants/remote/discovery/static.py
fakts_next/grants/remote/discovery/utils.py
fakts_next/grants/remote/discovery/well_known.py
fakts_next/grants/remote/discovery/qt/__init__.py
fakts_next/grants/remote/discovery/qt/selectable_beacon.py
fakts_next-3.0.0.dist-info/METADATA
fakts_next-3.0.0.dist-info/WHEEL
fakts_next-3.0.0.dist-info/entry_points.txt
fakts_next-3.0.0.dist-info/RECORD
