Metadata-Version: 2.4
Name: fakts-next
Version: 3.0.0
Summary: asynchronous configuration provider ( tailored to support dynamic client-server relations)
Author-email: jhnnsrs <jhnnsrs@gmail.com>
License-Expression: MIT
Requires-Python: >=3.11
Requires-Dist: aiohttp>=3.11.18
Requires-Dist: certifi>=2025.4.26
Requires-Dist: koil>=2.0.4
Requires-Dist: oauthlib>=3.3.1
Requires-Dist: pydantic>2
Requires-Dist: pyyaml>=6.0.2
